llm_party/__init__.py
llm_party/logger.py
llm_party/session.py
llm_party/attendee/__init__.py
llm_party/attendee/attendee_utils.py
llm_party/attendee/base/__init__.py
llm_party/attendee/base/base_attendee.py
llm_party/attendee/base/base_trait.py
llm_party/attendee/custom/__init__.py
llm_party/attendee/custom/custom_instruction.yaml
llm_party/attendee/custom/demo_attendee.py
llm_party/attendee/default/__init__.py
llm_party/attendee/default/default_attendee.py
llm_party/attendee/default/default_attendee_trait.py
llm_party/attendee/default/default_instruction.yaml
llm_party/controller/__init__.py
llm_party/controller/session_controller.py
llm_party/demo/idea_generation_init.yaml
llm_party/demo/save_dir/idea_generation_demo.yaml
llm_party/demo/save_dir/idea_generation_demo2.yaml
llm_party/model/__init__.py
llm_party/model/session_models.py
llm_party/registry/__init__.py
llm_party/registry/attendee_registry.py
llm_party/registry/instruction_registry.py
llm_party/scripts/__init__.py
llm_party/scripts/cli.py
llm_party/service/__init__.py
llm_party/service/session_service.py
tests/__init__.py
tests/test_session.py
tests/attendee/__init__.py
tests/attendee/default/__init__.py
tests/attendee/default/test_default_attendee.py
tests/attendee/demo/__init__.py
tests/attendee/demo/test_demo_attendee.py
tests/controller/__init__.py
tests/controller/test_session_controller.py
tests/model/__init__.py
tests/model/test_session_models.py
tests/scripts/__init__.py
tests/scripts/test_cli.py
tests/service/__init__.py
tests/service/test_session_service.py
llm_party-0.1.4.dist-info/METADATA
llm_party-0.1.4.dist-info/WHEEL
llm_party-0.1.4.dist-info/top_level.txt
llm_party-0.1.4.dist-info/RECORD
