Metadata-Version: 2.1
Name: llm-party
Version: 0.1.4
Summary: UNKNOWN
Home-page: https://github.com/sudodo/llm_party
Author: Akihito Sudo
Author-email: akihito.s.gm@gmail.com
License: UNKNOWN
Platform: UNKNOWN
Requires-Dist: llm-wrap ==0.1.2
Requires-Dist: marshmallow ==3.20.1
Requires-Dist: PyYAML ==6.0.1
